Metadata-Version: 2.1
Name: ont-spectre
Version: 0.3.3
Summary: Oxford Nanopore Technologies Plc. fork of Spectre CNV caller
Home-page: https://github.com/epi2me-labs/ont-spectre
Author: epi2melabs
Author-email: epi2melabs@nanoporetech.com
Requires-Python: >=3.8
License-File: LICENSE.md
Requires-Dist: pysam>=0.22.0
Requires-Dist: numpy>=1.24.3
Requires-Dist: pandas>=2.0.1
Requires-Dist: matplotlib>=3.7.1
Requires-Dist: scipy>=1.10.1
Requires-Dist: polars[pyarrow]>=0.19.15
Requires-Dist: setuptools>=42.0.0
